waffle/__init__.py
waffle/admin.py
waffle/apps.py
waffle/decorators.py
waffle/defaults.py
waffle/jinja.py
waffle/managers.py
waffle/middleware.py
waffle/mixins.py
waffle/models.py
waffle/py.typed
waffle/signals.py
waffle/testutils.py
waffle/urls.py
waffle/utils.py
waffle/views.py
waffle/locale/cs/LC_MESSAGES/django.mo
waffle/locale/en_US/LC_MESSAGES/django.mo
waffle/locale/it/LC_MESSAGES/django.mo
waffle/locale/ru/LC_MESSAGES/django.mo
waffle/management/__init__.py
waffle/management/commands/__init__.py
waffle/management/commands/waffle_delete.py
waffle/management/commands/waffle_flag.py
waffle/management/commands/waffle_sample.py
waffle/management/commands/waffle_switch.py
waffle/migrations/0001_initial.py
waffle/migrations/0002_auto_20161201_0958.py
waffle/migrations/0003_update_strings_for_i18n.py
waffle/migrations/0004_update_everyone_nullbooleanfield.py
waffle/migrations/__init__.py
waffle/templates/waffle/waffle.js
waffle/templatetags/__init__.py
waffle/templatetags/waffle_tags.py
waffle/tests/__init__.py
waffle/tests/base.py
waffle/tests/test_admin.py
waffle/tests/test_decorators.py
waffle/tests/test_management.py
waffle/tests/test_middleware.py
waffle/tests/test_mixin.py
waffle/tests/test_models.py
waffle/tests/test_templates.py
waffle/tests/test_testutils.py
waffle/tests/test_utils.py
waffle/tests/test_views.py
waffle/tests/test_waffle.py
django_waffle-5.0.0.dist-info/METADATA
django_waffle-5.0.0.dist-info/WHEEL
django_waffle-5.0.0.dist-info/top_level.txt
django_waffle-5.0.0.dist-info/RECORD
